use num_enum::{FromPrimitive, IntoPrimitive};

#[derive(Debug, Clone, Copy, PartialEq, Eq, IntoPrimitive, FromPrimitive)]
#[repr(u8)]
pub enum Opcode {
    Nop = 0x0,
    AconstNull = 0x1,
    IconstM1 = 0x2,
    Iconst0 = 0x3,
    Iconst1 = 0x4,
    Iconst2 = 0x5,
    Iconst3 = 0x6,
    Iconst4 = 0x7,
    Iconst5 = 0x8,
    Lconst0 = 0x9,
    Lconst1 = 0xa,
    Fconst0 = 0xb,
    Fconst1 = 0xc,
    Fconst2 = 0xd,
    Dconst0 = 0xe,
    Dconst1 = 0xf,

    Bipush = 0x10,
    Sipush = 0x11,
    Ldc = 0x12,
    LdcW = 0x13,
    Ldc2W = 0x14,
    Iload = 0x15,
    Lload = 0x16,
    Fload = 0x17,
    Dload = 0x18,
    Aload = 0x19,
    Iload0 = 0x1a,
    Iload1 = 0x1b,
    Iload2 = 0x1c,
    Iload3 = 0x1d,
    Lload0 = 0x1e,
    Lload1 = 0x1f,

    Lload2 = 0x20,
    Lload3 = 0x21,
    Fload0 = 0x22,
    Fload1 = 0x23,
    Fload2 = 0x24,
    Fload3 = 0x25,
    Dload0 = 0x26,
    Dload1 = 0x27,
    Dload2 = 0x28,
    Dload3 = 0x29,
    Aload0 = 0x2a,
    Aload1 = 0x2b,
    Aload2 = 0x2c,
    Aload3 = 0x2d,
    Iaload = 0x2e,
    Laload = 0x2f,

    Faload = 0x30,
    Daload = 0x31,
    Aaload = 0x32,
    Baload = 0x33,
    Caload = 0x34,
    Saload = 0x35,
    Istore = 0x36,
    Lstore = 0x37,
    Fstore = 0x38,
    Dstore = 0x39,
    Astore = 0x3a,
    Istore0 = 0x3b,
    Istore1 = 0x3c,
    Istore2 = 0x3d,
    Istore3 = 0x3e,
    Lstore0 = 0x3f,

    Lstore1 = 0x40,
    Lstore2 = 0x41,
    Lstore3 = 0x42,
    Fstore0 = 0x43,
    Fstore1 = 0x44,
    Fstore2 = 0x45,
    Fstore3 = 0x46,
    Dstore0 = 0x47,
    Dstore1 = 0x48,
    Dstore2 = 0x49,
    Dstore3 = 0x4a,
    Astore0 = 0x4b,
    Astore1 = 0x4c,
    Astore2 = 0x4d,
    Astore3 = 0x4e,
    Iastore = 0x4f,

    Lastore = 0x50,
    Fastore = 0x51,
    Dastore = 0x52,
    Aastore = 0x53,
    Bastore = 0x54,
    Castore = 0x55,
    Sastore = 0x56,
    Pop = 0x57,
    Pop2 = 0x58,
    Dup = 0x59,
    DupX1 = 0x5a,
    DupX2 = 0x5b,
    Dup2 = 0x5c,
    Dup2X1 = 0x5d,
    Dup2X2 = 0x5e,
    Swap = 0x5f,

    Iadd = 0x60,
    Ladd = 0x61,
    Fadd = 0x62,
    Dadd = 0x63,
    Isub = 0x64,
    Lsub = 0x65,
    Fsub = 0x66,
    Dsub = 0x67,
    Imul = 0x68,
    Lmul = 0x69,
    Fmul = 0x6a,
    Dmul = 0x6b,
    Idiv = 0x6c,
    Ldiv = 0x6d,
    Fdiv = 0x6e,
    Ddiv = 0x6f,

    Irem = 0x70,
    Lrem = 0x71,
    Frem = 0x72,
    Drem = 0x73,
    Ineg = 0x74,
    Lneg = 0x75,
    Fneg = 0x76,
    Dneg = 0x77,
    Ishl = 0x78,
    Lshl = 0x79,
    Ishr = 0x7a,
    Lshr = 0x7b,
    Iushr = 0x7c,
    Lushr = 0x7d,
    Iand = 0x7e,
    Land = 0x7f,

    Ior = 0x80,
    Lor = 0x81,
    Ixor = 0x82,
    Lxor = 0x83,
    Iinc = 0x84,
    I2l = 0x85,
    I2f = 0x86,
    I2d = 0x87,
    L2i = 0x88,
    L2f = 0x89,
    L2d = 0x8a,
    F2i = 0x8b,
    F2l = 0x8c,
    F2d = 0x8d,
    D2i = 0x8e,
    D2l = 0x8f,

    D2f = 0x90,
    I2b = 0x91,
    I2c = 0x92,
    I2s = 0x93,
    Lcmp = 0x94,
    Fcmpl = 0x95,
    Fcmpg = 0x96,
    Dcmpl = 0x97,
    Dcmpg = 0x98,
    Ifeq = 0x99,
    Ifne = 0x9a,
    Iflt = 0x9b,
    Ifge = 0x9c,
    Ifgt = 0x9d,
    Ifle = 0x9e,
    IfIcmpeq = 0x9f,

    IfIcmpne = 0xa0,
    IfIcmplt = 0xa1,
    IfIcmpge = 0xa2,
    IfIcmpgt = 0xa3,
    IfIcmple = 0xa4,
    IfAcmpeq = 0xa5,
    IfAcmpne = 0xa6,
    Goto = 0xa7,
    Jsr = 0xa8,
    Ret = 0xa9,
    Tableswitch = 0xaa,
    Lookupswitch = 0xab,
    Ireturn = 0xac,
    Lreturn = 0xad,
    Freturn = 0xae,
    Dreturn = 0xaf,

    Areturn = 0xb0,
    Return = 0xb1,
    Getstatic = 0xb2,
    Putstatic = 0xb3,
    Getfield = 0xb4,
    Putfield = 0xb5,
    Invokevirtual = 0xb6,
    Invokespecial = 0xb7,
    Invokestatic = 0xb8,
    Invokeinterface = 0xb9,
    Invokedynamic = 0xba,
    New = 0xbb,
    Newarray = 0xbc,
    Anewarray = 0xbd,
    Arraylength = 0xbe,
    Athrow = 0xbf,

    Checkcast = 0xc0,
    Instanceof = 0xc1,
    Monitorenter = 0xc2,
    Monitorexit = 0xc3,
    Wide = 0xc4,
    Multianewarray = 0xc5,
    Ifnull = 0xc6,
    Ifnonnull = 0xc7,
    GotoW = 0xc8,
    JsrW = 0xc9,

/// RESERVED
    Breakpoint = 0xca,
    #[num_enum(default)]
    ReservedFuture,

    Impdep1 = 0xfe,
    Impdep2 = 0xff,
}

impl Opcode {
    pub const fn immediates(self) -> u8 {
        match self {
            Opcode::Nop => 0,
            Opcode::AconstNull => 0,
            Opcode::IconstM1 => 0,
            Opcode::Iconst0 => 0,
            Opcode::Iconst1 => 0,
            Opcode::Iconst2 => 0,
            Opcode::Iconst3 => 0,
            Opcode::Iconst4 => 0,
            Opcode::Iconst5 => 0,
            Opcode::Lconst0 => 0,
            Opcode::Lconst1 => 0,
            Opcode::Fconst0 => 0,
            Opcode::Fconst1 => 0,
            Opcode::Fconst2 => 0,
            Opcode::Dconst0 => 0,
            Opcode::Dconst1 => 0,
            Opcode::Bipush => 1,
            Opcode::Sipush => 2,
            Opcode::Ldc => 1,
            Opcode::LdcW => 2,
            Opcode::Ldc2W => 2,
            Opcode::Iload => 1,
            Opcode::Lload => 1,
            Opcode::Fload => 1,
            Opcode::Dload => 1,
            Opcode::Aload => 1,
            Opcode::Iload0 => 0,
            Opcode::Iload1 => 0,
            Opcode::Iload2 => 0,
            Opcode::Iload3 => 0,
            Opcode::Lload0 => 0,
            Opcode::Lload1 => 0,
            Opcode::Lload2 => 0,
            Opcode::Lload3 => 0,
            Opcode::Fload0 => 0,
            Opcode::Fload1 => 0,
            Opcode::Fload2 => 0,
            Opcode::Fload3 => 0,
            Opcode::Dload0 => 0,
            Opcode::Dload1 => 0,
            Opcode::Dload2 => 0,
            Opcode::Dload3 => 0,
            Opcode::Aload0 => 0,
            Opcode::Aload1 => 0,
            Opcode::Aload2 => 0,
            Opcode::Aload3 => 0,
            Opcode::Iaload => 0,
            Opcode::Laload => 0,
            Opcode::Faload => 0,
            Opcode::Daload => 0,
            Opcode::Aaload => 0,
            Opcode::Baload => 0,
            Opcode::Caload => 0,
            Opcode::Saload => 0,
            Opcode::Istore => 1,
            Opcode::Lstore => 1,
            Opcode::Fstore => 1,
            Opcode::Dstore => 1,
            Opcode::Astore => 1,
            Opcode::Istore0 => 0,
            Opcode::Istore1 => 0,
            Opcode::Istore2 => 0,
            Opcode::Istore3 => 0,
            Opcode::Lstore0 => 0,
            Opcode::Lstore1 => 0,
            Opcode::Lstore2 => 0,
            Opcode::Lstore3 => 0,
            Opcode::Fstore0 => 0,
            Opcode::Fstore1 => 0,
            Opcode::Fstore2 => 0,
            Opcode::Fstore3 => 0,
            Opcode::Dstore0 => 0,
            Opcode::Dstore1 => 0,
            Opcode::Dstore2 => 0,
            Opcode::Dstore3 => 0,
            Opcode::Astore0 => 0,
            Opcode::Astore1 => 0,
            Opcode::Astore2 => 0,
            Opcode::Astore3 => 0,
            Opcode::Iastore => 0,
            Opcode::Lastore => 0,
            Opcode::Fastore => 0,
            Opcode::Dastore => 0,
            Opcode::Aastore => 0,
            Opcode::Bastore => 0,
            Opcode::Castore => 0,
            Opcode::Sastore => 0,
            Opcode::Pop => 0,
            Opcode::Pop2 => 0,
            Opcode::Dup => 0,
            Opcode::DupX1 => 0,
            Opcode::DupX2 => 0,
            Opcode::Dup2 => 0,
            Opcode::Dup2X1 => 0,
            Opcode::Dup2X2 => 0,
            Opcode::Swap => 0,
            Opcode::Iadd => 0,
            Opcode::Ladd => 0,
            Opcode::Fadd => 0,
            Opcode::Dadd => 0,
            Opcode::Isub => 0,
            Opcode::Lsub => 0,
            Opcode::Fsub => 0,
            Opcode::Dsub => 0,
            Opcode::Imul => 0,
            Opcode::Lmul => 0,
            Opcode::Fmul => 0,
            Opcode::Dmul => 0,
            Opcode::Idiv => 0,
            Opcode::Ldiv => 0,
            Opcode::Fdiv => 0,
            Opcode::Ddiv => 0,
            Opcode::Irem => 0,
            Opcode::Lrem => 0,
            Opcode::Frem => 0,
            Opcode::Drem => 0,
            Opcode::Ineg => 0,
            Opcode::Lneg => 0,
            Opcode::Fneg => 0,
            Opcode::Dneg => 0,
            Opcode::Ishl => 0,
            Opcode::Lshl => 0,
            Opcode::Ishr => 0,
            Opcode::Lshr => 0,
            Opcode::Iushr => 0,
            Opcode::Lushr => 0,
            Opcode::Iand => 0,
            Opcode::Land => 0,
            Opcode::Ior => 0,
            Opcode::Lor => 0,
            Opcode::Ixor => 0,
            Opcode::Lxor => 0,
            Opcode::Iinc => 2,
            Opcode::I2l => 0,
            Opcode::I2f => 0,
            Opcode::I2d => 0,
            Opcode::L2i => 0,
            Opcode::L2f => 0,
            Opcode::L2d => 0,
            Opcode::F2i => 0,
            Opcode::F2l => 0,
            Opcode::F2d => 0,
            Opcode::D2i => 0,
            Opcode::D2l => 0,
            Opcode::D2f => 0,
            Opcode::I2b => 0,
            Opcode::I2c => 0,
            Opcode::I2s => 0,
            Opcode::Lcmp => 0,
            Opcode::Fcmpl => 0,
            Opcode::Fcmpg => 0,
            Opcode::Dcmpl => 0,
            Opcode::Dcmpg => 0,
            Opcode::Ifeq => 2,
            Opcode::Ifne => 2,
            Opcode::Iflt => 2,
            Opcode::Ifge => 2,
            Opcode::Ifgt => 2,
            Opcode::Ifle => 2,
            Opcode::IfIcmpeq => 2,
            Opcode::IfIcmpne => 2,
            Opcode::IfIcmplt => 2,
            Opcode::IfIcmpge => 2,
            Opcode::IfIcmpgt => 2,
            Opcode::IfIcmple => 2,
            Opcode::IfAcmpeq => 2,
            Opcode::IfAcmpne => 2,
            Opcode::Goto => 2,
            Opcode::Jsr => 2,
            Opcode::Ret => 1,
            Opcode::Tableswitch => 16 /* + */,
            Opcode::Lookupswitch => 8 /* + */,
            Opcode::Ireturn => 0,
            Opcode::Lreturn => 0,
            Opcode::Freturn => 0,
            Opcode::Dreturn => 0,
            Opcode::Areturn => 0,
            Opcode::Return => 0,
            Opcode::Getstatic => 2,
            Opcode::Putstatic => 2,
            Opcode::Getfield => 2,
            Opcode::Putfield => 2,
            Opcode::Invokevirtual => 2,
            Opcode::Invokespecial => 2,
            Opcode::Invokestatic => 2,
            Opcode::Invokeinterface => 4,
            Opcode::Invokedynamic => 4,
            Opcode::New => 2,
            Opcode::Newarray => 1,
            Opcode::Anewarray => 2,
            Opcode::Arraylength => 0,
            Opcode::Athrow => 0,
            Opcode::Checkcast => 2,
            Opcode::Instanceof => 2,
            Opcode::Monitorenter => 0,
            Opcode::Monitorexit => 0,
            Opcode::Wide => 3 /* or 5 with iinc */,
            Opcode::Multianewarray => 3,
            Opcode::Ifnull => 2,
            Opcode::Ifnonnull => 2,
            Opcode::GotoW => 4,
            Opcode::JsrW => 4,

            Opcode::Breakpoint => 0,
            Opcode::ReservedFuture => 0,
            Opcode::Impdep1 => 0,
            Opcode::Impdep2 => 0,
        }
    }
    pub const fn mnemonic(self) -> &'static str {
        match self {
            Opcode::Nop => "nop",
            Opcode::AconstNull => "aconst_null",
            Opcode::IconstM1 => "iconst_m1",
            Opcode::Iconst0 => "iconst_0",
            Opcode::Iconst1 => "iconst_1",
            Opcode::Iconst2 => "iconst_2",
            Opcode::Iconst3 => "iconst_3",
            Opcode::Iconst4 => "iconst_4",
            Opcode::Iconst5 => "iconst_5",
            Opcode::Lconst0 => "lconst_0",
            Opcode::Lconst1 => "lconst_1",
            Opcode::Fconst0 => "fconst_0",
            Opcode::Fconst1 => "fconst_1",
            Opcode::Fconst2 => "fconst_2",
            Opcode::Dconst0 => "dconst_0",
            Opcode::Dconst1 => "dconst_1",
            Opcode::Bipush => "bipush",
            Opcode::Sipush => "sipush",
            Opcode::Ldc => "ldc",
            Opcode::LdcW => "ldc_w",
            Opcode::Ldc2W => "ldc2_w",
            Opcode::Iload => "iload",
            Opcode::Lload => "lload",
            Opcode::Fload => "fload",
            Opcode::Dload => "dload",
            Opcode::Aload => "aload",
            Opcode::Iload0 => "iload_0",
            Opcode::Iload1 => "iload_1",
            Opcode::Iload2 => "iload_2",
            Opcode::Iload3 => "iload_3",
            Opcode::Lload0 => "lload_0",
            Opcode::Lload1 => "lload_1",
            Opcode::Lload2 => "lload_2",
            Opcode::Lload3 => "lload_3",
            Opcode::Fload0 => "fload_0",
            Opcode::Fload1 => "fload_1",
            Opcode::Fload2 => "fload_2",
            Opcode::Fload3 => "fload_3",
            Opcode::Dload0 => "dload_0",
            Opcode::Dload1 => "dload_1",
            Opcode::Dload2 => "dload_2",
            Opcode::Dload3 => "dload_3",
            Opcode::Aload0 => "aload_0",
            Opcode::Aload1 => "aload_1",
            Opcode::Aload2 => "aload_2",
            Opcode::Aload3 => "aload_3",
            Opcode::Iaload => "iaload",
            Opcode::Laload => "laload",
            Opcode::Faload => "faload",
            Opcode::Daload => "daload",
            Opcode::Aaload => "aaload",
            Opcode::Baload => "baload",
            Opcode::Caload => "caload",
            Opcode::Saload => "saload",
            Opcode::Istore => "istore",
            Opcode::Lstore => "lstore",
            Opcode::Fstore => "fstore",
            Opcode::Dstore => "dstore",
            Opcode::Astore => "astore",
            Opcode::Istore0 => "istore_0",
            Opcode::Istore1 => "istore_1",
            Opcode::Istore2 => "istore_2",
            Opcode::Istore3 => "istore_3",
            Opcode::Lstore0 => "lstore_0",
            Opcode::Lstore1 => "lstore_1",
            Opcode::Lstore2 => "lstore_2",
            Opcode::Lstore3 => "lstore_3",
            Opcode::Fstore0 => "fstore_0",
            Opcode::Fstore1 => "fstore_1",
            Opcode::Fstore2 => "fstore_2",
            Opcode::Fstore3 => "fstore_3",
            Opcode::Dstore0 => "dstore_0",
            Opcode::Dstore1 => "dstore_1",
            Opcode::Dstore2 => "dstore_2",
            Opcode::Dstore3 => "dstore_3",
            Opcode::Astore0 => "astore_0",
            Opcode::Astore1 => "astore_1",
            Opcode::Astore2 => "astore_2",
            Opcode::Astore3 => "astore_3",
            Opcode::Iastore => "iastore",
            Opcode::Lastore => "lastore",
            Opcode::Fastore => "fastore",
            Opcode::Dastore => "dastore",
            Opcode::Aastore => "aastore",
            Opcode::Bastore => "bastore",
            Opcode::Castore => "castore",
            Opcode::Sastore => "sastore",
            Opcode::Pop => "pop",
            Opcode::Pop2 => "pop2",
            Opcode::Dup => "dup",
            Opcode::DupX1 => "dup_x1",
            Opcode::DupX2 => "dup_x2",
            Opcode::Dup2 => "dup2",
            Opcode::Dup2X1 => "dup2_x1",
            Opcode::Dup2X2 => "dup2_x2",
            Opcode::Swap => "swap",
            Opcode::Iadd => "iadd",
            Opcode::Ladd => "ladd",
            Opcode::Fadd => "fadd",
            Opcode::Dadd => "dadd",
            Opcode::Isub => "isub",
            Opcode::Lsub => "lsub",
            Opcode::Fsub => "fsub",
            Opcode::Dsub => "dsub",
            Opcode::Imul => "imul",
            Opcode::Lmul => "lmul",
            Opcode::Fmul => "fmul",
            Opcode::Dmul => "dmul",
            Opcode::Idiv => "idiv",
            Opcode::Ldiv => "ldiv",
            Opcode::Fdiv => "fdiv",
            Opcode::Ddiv => "ddiv",
            Opcode::Irem => "irem",
            Opcode::Lrem => "lrem",
            Opcode::Frem => "frem",
            Opcode::Drem => "drem",
            Opcode::Ineg => "ineg",
            Opcode::Lneg => "lneg",
            Opcode::Fneg => "fneg",
            Opcode::Dneg => "dneg",
            Opcode::Ishl => "ishl",
            Opcode::Lshl => "lshl",
            Opcode::Ishr => "ishr",
            Opcode::Lshr => "lshr",
            Opcode::Iushr => "iushr",
            Opcode::Lushr => "lushr",
            Opcode::Iand => "iand",
            Opcode::Land => "land",
            Opcode::Ior => "ior",
            Opcode::Lor => "lor",
            Opcode::Ixor => "ixor",
            Opcode::Lxor => "lxor",
            Opcode::Iinc => "iinc",
            Opcode::I2l => "i2l",
            Opcode::I2f => "i2f",
            Opcode::I2d => "i2d",
            Opcode::L2i => "l2i",
            Opcode::L2f => "l2f",
            Opcode::L2d => "l2d",
            Opcode::F2i => "f2i",
            Opcode::F2l => "f2l",
            Opcode::F2d => "f2d",
            Opcode::D2i => "d2i",
            Opcode::D2l => "d2l",
            Opcode::D2f => "d2f",
            Opcode::I2b => "i2b",
            Opcode::I2c => "i2c",
            Opcode::I2s => "i2s",
            Opcode::Lcmp => "lcmp",
            Opcode::Fcmpl => "fcmpl",
            Opcode::Fcmpg => "fcmpg",
            Opcode::Dcmpl => "dcmpl",
            Opcode::Dcmpg => "dcmpg",
            Opcode::Ifeq => "ifeq",
            Opcode::Ifne => "ifne",
            Opcode::Iflt => "iflt",
            Opcode::Ifge => "ifge",
            Opcode::Ifgt => "ifgt",
            Opcode::Ifle => "ifle",
            Opcode::IfIcmpeq => "if_icmpeq",
            Opcode::IfIcmpne => "if_icmpne",
            Opcode::IfIcmplt => "if_icmplt",
            Opcode::IfIcmpge => "if_icmpge",
            Opcode::IfIcmpgt => "if_icmpgt",
            Opcode::IfIcmple => "if_icmple",
            Opcode::IfAcmpeq => "if_acmpeq",
            Opcode::IfAcmpne => "if_acmpne",
            Opcode::Goto => "goto",
            Opcode::Jsr => "jsr",
            Opcode::Ret => "ret",
            Opcode::Tableswitch => "tableswitch",
            Opcode::Lookupswitch => "lookupswitch",
            Opcode::Ireturn => "ireturn",
            Opcode::Lreturn => "lreturn",
            Opcode::Freturn => "freturn",
            Opcode::Dreturn => "dreturn",
            Opcode::Areturn => "areturn",
            Opcode::Return => "return",
            Opcode::Getstatic => "getstatic",
            Opcode::Putstatic => "putstatic",
            Opcode::Getfield => "getfield",
            Opcode::Putfield => "putfield",
            Opcode::Invokevirtual => "invokevirtual",
            Opcode::Invokespecial => "invokespecial",
            Opcode::Invokestatic => "invokestatic",
            Opcode::Invokeinterface => "invokeinterface",
            Opcode::Invokedynamic => "invokedynamic",
            Opcode::New => "new",
            Opcode::Newarray => "newarray",
            Opcode::Anewarray => "anewarray",
            Opcode::Arraylength => "arraylength",
            Opcode::Athrow => "athrow",
            Opcode::Checkcast => "checkcast",
            Opcode::Instanceof => "instanceof",
            Opcode::Monitorenter => "monitorenter",
            Opcode::Monitorexit => "monitorexit",
            Opcode::Wide => "wide",
            Opcode::Multianewarray => "multianewarray",
            Opcode::Ifnull => "ifnull",
            Opcode::Ifnonnull => "ifnonnull",
            Opcode::GotoW => "goto_w",
            Opcode::JsrW => "jsr_w",

            Opcode::Breakpoint => "breakpoint",
            Opcode::ReservedFuture => "reserved_future",
            Opcode::Impdep1 => "impdep1",
            Opcode::Impdep2 => "impdep2",
        }
    }
}